aiogeoip/__init__.py
aiogeoip/aio.py
aiogeoip/cache.py
aiogeoip/geoip.py
aiogeoip/model.py
aiogeoip/requests_geoip.py
aiogeoip/urllib_geoip.py
aiogeoip/utils.py
aiogeoip/version.py
aiogeoip-1.0.dist-info/LICENSE
aiogeoip-1.0.dist-info/METADATA
aiogeoip-1.0.dist-info/WHEEL
aiogeoip-1.0.dist-info/top_level.txt
aiogeoip-1.0.dist-info/RECORD
