Metadata-Version: 2.1
Name: aiogeoip
Version: 1.0
Summary: Real asynchronous geolocation by IP address with asyncio support.
Home-page: https://github.com/py-paulo/aiogeoip.git
Author: Paulo Roberto <paulo.rb.beserra@gmail.com>
Author-email: paulo.rb.beserra@gmail.com
License: MIT
Project-URL: GitHub: issues, https://github.com/py-paulo/aiogeoip/issues
Project-URL: GitHub: repo, https://github.com/py-paulo/aiogeoip
Project-URL: Read the Docs, https://aiogeoip.readthedocs.io/en/latest/
Keywords: aio,python,asyncio,geoip,io,geolocation
Platform: UNKNOWN
Classifier: Environment :: Console
Classifier: Programming Language :: Python :: 3.6
Classifier: Programming Language :: Python :: 3.7
Classifier: Programming Language :: Python :: 3.8
Classifier: Operating System :: POSIX
Classifier: Operating System :: MacOS :: MacOS X
Classifier: Operating System :: Microsoft :: Windows
Classifier: Framework :: AsyncIO
Provides: aiogeoip
Requires-Python: >=3.6
License-File: LICENSE
Requires-Dist: aiohttp
Requires-Dist: requests
Requires-Dist: ujson
Requires-Dist: urllib3
